sequencing/__init__.py
sequencing/benchmarking.py
sequencing/calibration.py
sequencing/modes.py
sequencing/parameters.py
sequencing/pulses.py
sequencing/qasm.py
sequencing/system.py
sequencing/testing.py
sequencing/version.py
sequencing/gates/__init__.py
sequencing/gates/onequbit.py
sequencing/gates/twoqubit.py
sequencing/sequencing/__init__.py
sequencing/sequencing/basic.py
sequencing/sequencing/common.py
sequencing/sequencing/main.py
sequencing/test/__init__.py
sequencing/test/test_benchmarking.py
sequencing/test/test_calibration.py
sequencing/test/test_gates.py
sequencing/test/test_modes.py
sequencing/test/test_parameters.py
sequencing/test/test_pulses.py
sequencing/test/test_qasm.py
sequencing/test/test_rotations.py
sequencing/test/test_sequencing.py
sequencing/test/test_system.py
sequencing-1.2.0.dist-info/LICENSE
sequencing-1.2.0.dist-info/METADATA
sequencing-1.2.0.dist-info/WHEEL
sequencing-1.2.0.dist-info/top_level.txt
sequencing-1.2.0.dist-info/RECORD
